[

    {
    "country": "Cambodia",
    "city": "Phnom Penh"
    },
    {
    "country": "Cameroon",
    "city": "Yaounde"
    },
    {
    "country": "Canada",
    "city": "Ottawa"
    },
    {
    "country": "Cape Verde",
    "city": "Praia"
    },
    {
    "country": "Central African Republic",
    "city": "Bangui"
    },
    {
    "country": "Chad",
    "city": "N'Djamena"
    },
    {
    "country": "Chile",
    "city": "Santiago"
    },
    {
    "country": "China",
    "city": "Beijing"
    },
    {
    "country": "Colombia",
    "city": "Bogota"
    },
    {
    "country": "Comoros",
    "city": "Moroni"
    }
    
]